linlog/__init__.py
linlog/context.py
linlog/filters.py
linlog/formatters.py
linlog/handlers.py
linlog/utils.py
linlog_py-0.1.6.dist-info/METADATA
linlog_py-0.1.6.dist-info/WHEEL
linlog_py-0.1.6.dist-info/top_level.txt
linlog_py-0.1.6.dist-info/RECORD
