Metadata-Version: 2.4
Name: linlog-py
Version: 0.1.6
Summary: Simple Python logging utilities with custom formatters, daily rotation, and request ID tracking
Author-email: KuanLin <isu10122068a@gmail.com>
License: MIT
Keywords: logging,request-id,rotation,formatter,tracking
Classifier: Development Status :: 3 - Alpha
Classifier: Intended Audience :: Developers
Classifier: License :: OSI Approved :: MIT License
Classifier: Programming Language :: Python :: 3
Classifier: Programming Language :: Python :: 3.8
Classifier: Programming Language :: Python :: 3.9
Classifier: Programming Language :: Python :: 3.10
Classifier: Programming Language :: Python :: 3.11
Classifier: Programming Language :: Python :: 3.12
Classifier: Topic :: System :: Logging
Requires-Python: >=3.8
Provides-Extra: dev
Requires-Dist: pytest>=7.0; extra == "dev"
